{
  "data": [
    {
      "id": "57d4852f3db7ac6c4f5dacfc"
    },
    {
      "id": "57d4852f3db7ac6c4f5dacfd"
    },
    {
      "id": "57d4852f3db7ac6c4f5dacfe"
    },
    {
      "id": "57d4852f3db7ac6c4f5dacff"
    },
    {
      "id": "57d4852f3db7ac6c4f5dad00"
    },
    {
      "id": "57d4852f3db7ac6c4f5dad01"
    },
    {
      "id": "57d4852f3db7ac6c4f5dad02"
    },
    {
      "id": "57d4852f3db7ac6c4f5dad03"
    },
    {
      "id": "57d4852f3db7ac6c4f5dad04"
    },
    {
      "id": "57d4852f3db7ac6c4f5dad05"
    },
    {
      "id": "57d4852f3db7ac6c4f5dad06"
    },
    {
      "id": "57d4852f3db7ac6c4f5dad07"
    },
    {
      "id": "57d4852f3db7ac6c4f5dad08"
    },
    {
      "id": "57d4852f3db7ac6c4f5dad09"
    },
    {
      "id": "57d4852f3db7ac6c4f5dad0a"
    },
    {
      "id": "57d4852f3db7ac6c4f5dad0b"
    },
    {
      "id": "57d4852f3db7ac6c4f5dad0c"
    },
    {
      "id": "57d4852f3db7ac6c4f5dad0d"
    },
    {
      "id": "57d4852f3db7ac6c4f5dad0e"
    },
    {
      "id": "57d4852f3db7ac6c4f5dad0f"
    },
    {
      "id": "57d4852f3db7ac6c4f5dad10"
    },
    {
      "id": "57d4852f3db7ac6c4f5dad11"
    },
    {
      "id": "57d4852f3db7ac6c4f5dad12"
    },
    {
      "id": "57d4852f3db7ac6c4f5dad13"
    },
    {
      "id": "57d4852f3db7ac6c4f5dad14"
    },
    {
      "id": "57d4852f3db7ac6c4f5dad15"
    },
    {
      "id": "57d4852f3db7ac6c4f5dad16"
    },
    {
      "id": "57d4852f3db7ac6c4f5dad17"
    },
    {
      "id": "57d4852f3db7ac6c4f5dad18"
    },
    {
      "id": "57d4852f3db7ac6c4f5dad19"
    }
  ]
}